kpii/__init__.py
kpii/detector.py
kpii-0.1.0.dist-info/METADATA
kpii-0.1.0.dist-info/WHEEL
kpii-0.1.0.dist-info/licenses/LICENSE
kpii-0.1.0.dist-info/RECORD
