Metadata-Version: 2.4
Name: kpii
Version: 0.1.0
Summary: 한국어 개인정보 탐지 및 마스킹 라이브러리
Project-URL: Homepage, https://github.com/sotthang/kpii
Project-URL: Bug Tracker, https://github.com/sotthang/kpii/issues
Author-email: HyeonSeop So <sotthang@gmail.com>
License-Expression: MIT
License-File: LICENSE
Classifier: License :: OSI Approved :: MIT License
Classifier: Operating System :: OS Independent
Classifier: Programming Language :: Python :: 3
Requires-Python: >=3.9
